Vivado Labs/Lab09/Lab09_task1/Lab09_task1.srcs/sources_1/new/alu_control.v
`timescale 1ns / 1ps
//////////////////////////////////////////////////////////////////////////////////
// Company: 
// Engineer: 
// 
// Create Date: 03/26/2026 10:51:00 AM
// Design Name: 
// Module Name: alu_control
// Project Name: 
// Target Devices: 
// Tool Versions: 
// Description: 
// 
// Dependencies: 
// 
// Revision:
// Revision 0.01 - File Created
// Additional Comments:
// 
//////////////////////////////////////////////////////////////////////////////////


module ALUControl(
    input [1:0] ALUOp,
    input [2:0] funct3,
    input [6:0] funct7,
    output reg [3:0] ALUControl
);

always @(*) begin
    case(ALUOp)

        // Load/Store ? ADD
        2'b00: ALUControl = 4'b0010;

        // Branch ? SUB (for BEQ)
        2'b01: ALUControl = 4'b0110;

        // R-type / I-type
        2'b10: begin
            case(funct3)

                3'b000: begin
                    if (funct7 == 7'b0100000)
                        ALUControl = 4'b0110; // SUB
                    else
                        ALUControl = 4'b0010; // ADD / ADDI
                end

                3'b001: ALUControl = 4'b1000; // SLL
                3'b101: ALUControl = 4'b1001; // SRL
                3'b111: ALUControl = 4'b0000; // AND
                3'b110: ALUControl = 4'b0001; // OR
                3'b100: ALUControl = 4'b0011; // XOR

                default: ALUControl = 4'b0000;
            endcase
        end

        default: ALUControl = 4'b0000;

    endcase
end

endmodule

Vivado Labs/Lab09/Lab09_task1/Lab09_task1.srcs/sources_1/new/main_control.v
`timescale 1ns / 1ps
//////////////////////////////////////////////////////////////////////////////////
// Company: 
// Engineer: 
// 
// Create Date: 03/26/2026 10:51:00 AM
// Design Name: 
// Module Name: main_control
// Project Name: 
// Target Devices: 
// Tool Versions: 
// Description: 
// 
// Dependencies: 
// 
// Revision:
// Revision 0.01 - File Created
// Additional Comments:
// 
//////////////////////////////////////////////////////////////////////////////////


module MainControl(
    input [6:0] opcode,
    output reg RegWrite,
    output reg ALUSrc,
    output reg MemRead,
    output reg MemWrite,
    output reg MemtoReg,
    output reg Branch,
    output reg [1:0] ALUOp
);

always @(*) begin
    // Default safe values
    RegWrite = 0;
    ALUSrc   = 0;
    MemRead  = 0;
    MemWrite = 0;
    MemtoReg = 0;
    Branch   = 0;
    ALUOp    = 2'b00;

    case(opcode)

        // R-type (ADD, SUB, SLL, SRL, AND, OR, XOR)
        7'b0110011: begin
            RegWrite = 1;
            ALUSrc   = 0;
            ALUOp    = 2'b10;
        end

        // I-type (ADDI)
        7'b0010011: begin
            RegWrite = 1;
            ALUSrc   = 1;
            ALUOp    = 2'b10;
        end

        // Load (LW, LH, LB)
        7'b0000011: begin
            RegWrite = 1;
            ALUSrc   = 1;
            MemRead  = 1;
            MemtoReg = 1;
            ALUOp    = 2'b00;
        end

        // Store (SW, SH, SB)
        7'b0100011: begin
            ALUSrc   = 1;
            MemWrite = 1;
            ALUOp    = 2'b00;
        end

        // Branch (BEQ)
        7'b1100011: begin
            Branch = 1;
            ALUOp  = 2'b01;
        end

        default: begin
            // Keep defaults (safe)
        end

    endcase
end

endmodule

Vivado Labs/Lab09/Lab09_task1/Lab09_task1.srcs/sources_1/new/testbench.v
`timescale 1ns / 1ps
//////////////////////////////////////////////////////////////////////////////////
// Company: 
// Engineer: 
// 
// Create Date: 03/26/2026 10:51:00 AM
// Design Name: 
// Module Name: testbench
// Project Name: 
// Target Devices: 
// Tool Versions: 
// Description: 
// 
// Dependencies: 
// 
// Revision:
// Revision 0.01 - File Created
// Additional Comments:
// 
//////////////////////////////////////////////////////////////////////////////////


`timescale 1ns/1ps

module tb_control;

reg [6:0] opcode;
reg [2:0] funct3;
reg [6:0] funct7;

wire RegWrite, ALUSrc, MemRead, MemWrite, MemtoReg, Branch;
wire [1:0] ALUOp;
wire [3:0] ALUControl;

// Instantiate Main Control
MainControl mc(
    .opcode(opcode),
    .RegWrite(RegWrite),
    .ALUSrc(ALUSrc),
    .MemRead(MemRead),
    .MemWrite(MemWrite),
    .MemtoReg(MemtoReg),
    .Branch(Branch),
    .ALUOp(ALUOp)
);

// Instantiate ALU Control
ALUControl alu_ctrl(
    .ALUOp(ALUOp),
    .funct3(funct3),
    .funct7(funct7),
    .ALUControl(ALUControl)
);

initial begin
    $dumpfile("control.vcd");
    $dumpvars(0, tb_control);

    // -------- R-TYPE --------
    opcode = 7'b0110011;

    // ADD
    funct3 = 3'b000; funct7 = 7'b0000000; #10;

    // SUB
    funct7 = 7'b0100000; #10;

    // SLL
    funct3 = 3'b001; funct7 = 7'b0000000; #10;

    // SRL
    funct3 = 3'b101; #10;

    // AND
    funct3 = 3'b111; #10;

    // OR
    funct3 = 3'b110; #10;

    // XOR
    funct3 = 3'b100; #10;

    // -------- I-TYPE (ADDI) --------
    opcode = 7'b0010011;
    funct3 = 3'b000; funct7 = 7'b0000000; #10;

    // -------- LOAD --------
    opcode = 7'b0000011; #10;

    // -------- STORE --------
    opcode = 7'b0100011; #10;

    // -------- BEQ --------
    opcode = 7'b1100011; #10;

    $finish;
end

endmodule

Vivado Labs/Lab09/Lab09_task1/Lab09_task1.sim/sim_1/behav/xsim/control.vcd
$date
   Thu Mar 26 12:43:02 2026
$end
$version
  2020.1
$end
$timescale
  1ps
$end
$scope module tb_control $end
$var reg 7 ! opcode [6:0] $end
$var reg 3 " funct3 [2:0] $end
$var reg 7 # funct7 [6:0] $end
$var wire 1 $ RegWrite $end
$var wire 1 % ALUSrc $end
$var wire 1 & MemRead $end
$var wire 1 ' MemWrite $end
$var wire 1 ( MemtoReg $end
$var wire 1 ) Branch $end
$var wire 2 * ALUOp [1:0] $end
$var wire 4 + ALUControl [3:0] $end
$scope module mc $end
$var wire 7 , opcode [6:0] $end
$var reg 1 - RegWrite $end
$var reg 1 . ALUSrc $end
$var reg 1 / MemRead $end
$var reg 1 0 MemWrite $end
$var reg 1 1 MemtoReg $end
$var reg 1 2 Branch $end
$var reg 2 3 ALUOp [1:0] $end
$upscope $end
$scope module alu_ctrl $end
$var wire 2 * ALUOp [1:0] $end
$var wire 3 4 funct3 [2:0] $end
$var wire 7 5 funct7 [6:0] $end
$var reg 4 6 ALUControl [3:0] $end
$upscope $end
$upscope $end
$enddefinitions $end
#0
$dumpvars
b110011 !
b0 "
b0 #
1$
0%
0&
0'
0(
0)
b10 *
b10 +
b110011 ,
1-
0.
0/
00
01
02
b10 3
b0 4
b0 5
b10 6
$end
#10000
b100000 #
b110 +
b100000 5
b110 6
#20000
b1 "
b0 #
b1000 +
b1 4
b0 5
b1000 6
#30000
b101 "
b1001 +
b101 4
b1001 6
#40000
b111 "
b0 +
b111 4
b0 6
#50000
b110 "
b1 +
b110 4
b1 6
#60000
b100 "
b11 +
b100 4
b11 6
#70000
b10011 !
b0 "
b0 #
1%
b10 *
b10 +
b10011 ,
1-
1.
0/
00
01
02
b10 3
b0 4
b10 6
#80000
b11 !
1&
1(
b0 *
b11 ,
1-
1.
1/
00
11
02
b0 3
b10 6
#90000
b100011 !
0$
0&
1'
0(
b100011 ,
0-
1.
0/
10
01
02
b0 3
#100000
b1100011 !
0%
0'
1)
b1 *
b110 +
b1100011 ,
0-
0.
0/
00
01
12
b1 3
b110 6
