Vivado Labs/Lab06/Lab06-CA_task2/Lab06-CA.srcs/sources_1/new/ALU.v
module ALU (
    input  [31:0] A,
    input  [31:0] B,
    input  [3:0]  ALUControl,
    output reg [31:0] ALUResult,
    output Zero
);

always @(*) begin
    case (ALUControl)
        4'b0000: ALUResult = A + B;               // ADD
        4'b0001: ALUResult = A - B;               // SUB
        4'b0010: ALUResult = A & B;               // AND
        4'b0011: ALUResult = A | B;               // OR
        4'b0100: ALUResult = A ^ B;               // XOR
        4'b0101: ALUResult = A << B[4:0];         // SLL (shift left logical)
        4'b0110: ALUResult = A >> B[4:0];         // SRL (shift right logical)
        4'b0111: ALUResult = (A < B) ? 32'b1 : 32'b0; // SLT
        default: ALUResult = 32'b0;
    endcase
end

assign Zero = (ALUResult == 32'b0);

endmodule

Vivado Labs/Lab06/Lab06-CA_task2/Lab06-CA.srcs/sources_1/new/ALU_tb.v
`timescale 1ns/1ps

module ALU_tb;

reg  [31:0] A, B;
reg  [3:0]  ALUControl;
wire [31:0] ALUResult;
wire Zero;

// Instantiate ALU
ALU uut (
    .A(A),
    .B(B),
    .ALUControl(ALUControl),
    .ALUResult(ALUResult),
    .Zero(Zero)
);
initial begin

    // Generate waveform file
    $dumpfile("ALU_waveform.vcd");
    $dumpvars(0, ALU_tb);

    // Test ADD
    A = 1; B = 1; ALUControl = 4'b0000; #10;
    
    // Test SUB
    A = 10; B = 1; ALUControl = 4'b0001; #10;

    // Test AND
    A = 8'hFF; B = 8'h00; ALUControl = 4'b0010; #10;

    // Test OR
    A = 8'hFA; B = 8'h00; ALUControl = 4'b0011; #10;

    // Test XOR
    A = 8'hAA; B = 8'hFF; ALUControl = 4'b0100; #10;

    // Test SLL
    A = 10; B = 2; ALUControl = 4'b0101; #10;

    // Test SRL
    A = 21; B = 3; ALUControl = 4'b0110; #10;

    // Test SLT
    A = 10; B = 5; ALUControl = 4'b0111; #10;

    // Test Zero flag
    A = 1; B = 5; ALUControl = 4'b0001; #10;

    $finish;
end

endmodule

Vivado Labs/Lab06/Lab06-CA_task2/Lab06-CA.sim/sim_1/behav/xsim/ALU_waveform.vcd
$date
   Thu Mar  5 07:39:12 2026
$end
$version
  2020.1
$end
$timescale
  1ps
$end
$scope module ALU_tb $end
$var reg 32 ! A [31:0] $end
$var reg 32 " B [31:0] $end
$var reg 4 # ALUControl [3:0] $end
$var wire 32 $ ALUResult [31:0] $end
$var wire 1 % Zero $end
$scope module uut $end
$var wire 32 & A [31:0] $end
$var wire 32 ' B [31:0] $end
$var wire 4 ( ALUControl [3:0] $end
$var reg 32 ) ALUResult [31:0] $end
$var wire 1 % Zero $end
$upscope $end
$upscope $end
$enddefinitions $end
#0
$dumpvars
b1 !
b1 "
b0 #
b10 $
0%
b1 &
b1 '
b0 (
b10 )
$end
#10000
b1010 !
b1 "
b1 #
b1001 $
b1010 &
b1 (
b1001 )
#20000
b11111111 !
b0 "
b10 #
b0 $
1%
b11111111 &
b0 '
b10 (
b0 )
#30000
b11111010 !
b0 "
b11 #
b11111010 $
0%
b11111010 &
b11 (
b11111010 )
#40000
b10101010 !
b11111111 "
b100 #
b1010101 $
b10101010 &
b11111111 '
b100 (
b1010101 )
#50000
b1010 !
b10 "
b101 #
b101000 $
b1010 &
b10 '
b101 (
b101000 )
#60000
b10101 !
b11 "
b110 #
b10 $
b10101 &
b11 '
b110 (
b10 )
#70000
b1010 !
b101 "
b111 #
b0 $
1%
b1010 &
b101 '
b111 (
b0 )
#80000
b1 !
b101 "
b1 #
b11111111111111111111111111111100 $
0%
b1 &
b1 (
b11111111111111111111111111111100 )
